deepdisc/__init__.py
deepdisc/_version.py
deepdisc/astrodet/DC2_public.py
deepdisc/astrodet/__init__.py
deepdisc/astrodet/astrodet.py
deepdisc/astrodet/colormap.py
deepdisc/astrodet/detectron.py
deepdisc/astrodet/hsc.py
deepdisc/astrodet/scarlet_catalog.py
deepdisc/astrodet/scarlet_nocatalog.py
deepdisc/astrodet/visualizer.py
deepdisc/data_format/__init__.py
deepdisc/data_format/augment_image.py
deepdisc/data_format/conversions.py
deepdisc/data_format/file_io.py
deepdisc/data_format/image_readers.py
deepdisc/data_format/register_data.py
deepdisc/data_format/annotation_functions/__init__.py
deepdisc/data_format/annotation_functions/annotate_dc2.py
deepdisc/data_format/annotation_functions/annotate_decam.py
deepdisc/data_format/annotation_functions/annotate_hsc.py
deepdisc/inference/__init__.py
deepdisc/inference/match_objects.py
deepdisc/inference/predictors.py
deepdisc/model/__init__.py
deepdisc/model/loaders.py
deepdisc/model/models.py
deepdisc/preprocessing/__init__.py
deepdisc/preprocessing/detection.py
deepdisc/preprocessing/get_data.py
deepdisc/preprocessing/process.py
deepdisc/training/__init__.py
deepdisc/training/trainers.py
deepdisc/utils/__init__.py
deepdisc/utils/parse_arguments.py
deepdisc-0.1.1.dist-info/LICENSE
deepdisc-0.1.1.dist-info/METADATA
deepdisc-0.1.1.dist-info/WHEEL
deepdisc-0.1.1.dist-info/top_level.txt
deepdisc-0.1.1.dist-info/RECORD
